sectec/__init__.py
sectec/main.py
sectec-1.2.dist-info/METADATA
sectec-1.2.dist-info/WHEEL
sectec-1.2.dist-info/top_level.txt
sectec-1.2.dist-info/RECORD
