Metadata-Version: 2.1
Name: sectec
Version: 1.2
Summary: Easy to use Webscraper module for python
Author: Ali Lodhi
Author-email: alilodhibusiness@gmail.com
Requires-Dist: requests ==2.31.0
Requires-Dist: bs4 ==0.0.2
